README.md
setup.py
sblapi/__init__.py
sblapi/sblapi.py
sblapi.egg-info/PKG-INFO
sblapi.egg-info/SOURCES.txt
sblapi.egg-info/dependency_links.txt
sblapi.egg-info/requires.txt
sblapi.egg-info/top_level.txt