Metadata-Version: 2.1
Name: sblapi
Version: 0.1.1
Summary: API for shieldbotlist.website.
Home-page: https://github.com/Shield-Bot-List/Shield-Bot-List-API/tree/py-api
Author: fire
Author-email: help@shieldbotlist.website
License: ISC
Platform: UNKNOWN
